salt_portal_backup/__about__.py
salt_portal_backup/__init__.py
salt_portal_backup/backup.py
salt_portal_backup/database.py
salt_portal_backup/salt_portal.py
salt_portal_backup/web_scraping.py
salt_portal_backup-0.1.1.dist-info/METADATA
salt_portal_backup-0.1.1.dist-info/WHEEL
salt_portal_backup-0.1.1.dist-info/entry_points.txt
salt_portal_backup-0.1.1.dist-info/licenses/LICENSE.txt
salt_portal_backup-0.1.1.dist-info/RECORD
