Metadata-Version: 2.4
Name: salt-portal-backup
Version: 0.1.1
Summary: Backup projects, stations, calibrations and measurements from Salt Portal to a SQLite database.
Project-URL: Documentation, https://github.com/rhkarls/salt-portal-backup#readme
Project-URL: Issues, https://github.com/rhkarls/salt-portal-backup/issues
Project-URL: Source, https://github.com/rhkarls/salt-portal-backup
Author-email: Reinert Huseby Karlsen <rhkarls@proton.me>
License-Expression: BSD-3-Clause
License-File: LICENSE.txt
Classifier: Development Status :: 4 - Beta
Classifier: Programming Language :: Python
Classifier: Programming Language :: Python :: 3.9
Classifier: Programming Language :: Python :: 3.10
Classifier: Programming Language :: Python :: 3.11
Classifier: Programming Language :: Python :: 3.12
Classifier: Programming Language :: Python :: 3.13
Classifier: Programming Language :: Python :: Implementation :: CPython
Classifier: Programming Language :: Python :: Implementation :: PyPy
Requires-Python: >=3.9
Requires-Dist: beautifulsoup4
Requires-Dist: click
Requires-Dist: numpy
Requires-Dist: pandas
Requires-Dist: requests
Requires-Dist: sqlalchemy
Requires-Dist: tqdm
